average_methylation/__init__.py
average_methylation/methylation_analysis.py
average_methylation-0.1.0.dist-info/LICENSE
average_methylation-0.1.0.dist-info/METADATA
average_methylation-0.1.0.dist-info/WHEEL
average_methylation-0.1.0.dist-info/top_level.txt
average_methylation-0.1.0.dist-info/RECORD
