Metadata-Version: 2.1
Name: average_methylation
Version: 0.1.0
Summary: A package to calculate average methylation scores.
Home-page: https://github.com/mrimis/average-methylation-calculation.git
Author: Your Name
Author-email: your.email@example.com
Classifier: Programming Language :: Python :: 3
Classifier: License :: OSI Approved :: MIT License
Classifier: Operating System :: OS Independent
Requires-Python: >=3.6
License-File: LICENSE
Requires-Dist: pandas >=1.0.1
Requires-Dist: numpy >=1.18.1
Provides-Extra: dev
Requires-Dist: pytest >=5.4.1 ; extra == 'dev'
